{
  "library_id": "bpl",
  "attraction_slug": "american-rep-theater",
  "status": "ok",
  "max_people": null,
  "max_adults": null,
  "max_children": null,
  "free_under_age": null,
  "savings_per_person_usd": null,
  "discount_percent": null,
  "discount_dollar_off": null,
  "eligibility_tags": [
    "all"
  ],
  "exclusions": [],
  "boosts": [],
  "notes": null,
  "raw": "617-547-8300 The American Repertory Theater (A.R.T.) at Harvard University is a leading force in the American theater, producing groundbreaking work that is driven by risk-taking and passionate inquiry. A.R.T. was founded in 1980 by Robert Brustein, who served as Artistic Director until 2002, when he was succeeded by Robert Woodruff. Diane Paulus began her tenure as Terrie and Bradley Bloom Artistic Director in 2008. Digital (downloadable via email) passes are available. Select your desired visit date from the calendar below.",
  "source_phrases": {}
}