{
  "library_id": "melrose",
  "attraction_slug": "mass-audubon-drumlin-farm",
  "status": "ok",
  "max_people": 4,
  "max_adults": null,
  "max_children": null,
  "eligibility": "all",
  "free_under_age": null,
  "savings_per_person_usd": null,
  "notes": null,
  "raw": "Mass Audubon Library Partner Admission Pass – Melrose Public Library Please visit https://www.massaudubon.org/get-outdoors/wildlife-sanctuaries/trails for hours of operation and the latest information, including safety guidelines. This is not a ticket. The library pass does not guarantee admission on a chosen date. This one-day Library Partner Admission Pass admits up to 4 people to a Mass Audubon wildlife sanctuary. With this pass, admission is discounted to $2 per visitor over the age of 2. This Admission Pass will not be accepted after May 31, 2027. Pass must be presented to Mass Audubon staff upon arrival for your wildlife sanctuary visit. Reserve your Melrose Public Library pass for desired date. You will receive a confirmation email with an \"Access Pass\" link (if you do not have an email account, a printed confirmation may be picked up at the Main Desk of the library). Funded by donations to the Melrose Public Library."
}