{
  "library_id": "woburn",
  "attraction_slug": "boston-childrens-museum",
  "status": "ok",
  "max_people": 4,
  "max_adults": null,
  "max_children": null,
  "free_under_age": 1,
  "savings_per_person_usd": null,
  "discount_percent": 50,
  "discount_dollar_off": null,
  "eligibility_tags": [
    "all"
  ],
  "exclusions": [],
  "boosts": [],
  "notes": null,
  "raw": "Woburn Public Library* Pass admits up to 4 people at 50% off admission price per person; children under 12 months free. Boston Children’s Museum 308 Congress Street Boston, MA 02210 (617) 426-6500 * Funded by the Friends of the WPL",
  "source_phrases": {
    "max_people": "up to 4 people",
    "free_under_age": "children under 12 months free",
    "discount_percent": "50% off"
  }
}