{
  "library_id": "cohasset",
  "attraction_slug": "uss-constitution-museum",
  "status": "ok",
  "max_people": 5,
  "max_adults": null,
  "max_children": null,
  "free_under_age": null,
  "savings_per_person_usd": null,
  "discount_percent": 100,
  "discount_dollar_off": null,
  "eligibility_tags": [
    "all"
  ],
  "exclusions": [],
  "boosts": [],
  "notes": null,
  "raw": "Building 22, Charlestown Navy Yard Charlestown, MA 02129 617-426-1812 Get Directions Print out this pass or display on phone and bring to the USS Constitution Museum box office. Pass holders will receive free admission to the museum. One pass allows free admission for up to 5 people per day. One pass per party, please. Please Note: Museum Hours - Open Daily; Winter Hours 10:00am - 5:00pm. Museum is closed Thanksgiving Day, Christmas Day, and New Year's Day. Update 01/12/2026 Visit museum website for more information. Zoo New England Learn More",
  "source_phrases": {
    "max_people": "up to 5 people",
    "discount_percent": "free admission"
  }
}