{
  "library_id": "brookline",
  "attraction_slug": "peabody-essex-museum",
  "status": "ok",
  "raw": "(978) 745-9500 For over 220 years, PEM has been dedicated to collecting, preserving, and showcasing compelling artwork throughout history and from around the world. The Peabody Essex Museum in Salem, Massachusetts, US, is a successor to the East India Marine Society, established in 1799. It combines the collections of the former Peabody Museum of Salem and the Essex Institute. Pass benefits: Admits up to 2 adults at $12 per person. Youth ages 16 and under receive free admission. Does not include admission to the Chinese House. Visit the Peabody Essex Museum's website. Digital (downloadable via email) passes are available. Select your desired visit date from the calendar below.",
  "capacity": {
    "kind": "people",
    "n": 2
  },
  "audience_policies": [
    {
      "audience": "Adult",
      "age_range": null,
      "count": 2,
      "form": "per-person-price",
      "value": 12
    },
    {
      "audience": "Youth",
      "age_range": {"min": null, "max": 16},
      "count": null,
      "form": "free",
      "value": null
    }
  ],
  "restrictions": {
    "blackout_dates": false,
    "weekdays_only": false,
    "seasonal": null,
    "reservation_required": false
  },
  "source_phrases": {
    "capacity.n": "up to 2 adults",
    "audience_policies[0].form": "$12 per person",
    "audience_policies[1].age_range.max": "Youth ages 16 and under",
    "audience_policies[1].form": "free admission"
  }
}
