{
  "library_id": "north-andover",
  "attraction_slug": "zoo-new-england",
  "status": "ok",
  "raw": "Each pass admits maximum of 6 people at $9 per adult and $6 per child. Children under 2 are admitted free. Valid for general daytime admission to Franklin Park Zoo or Stone Zoo only. Tickets are non-refundable, have no cash value, cannot be combined with other offers or discounts and cannot be replaced if lost or stolen. Not valid for ZooLights or Boston Lights.",
  "capacity": {
    "kind": "people",
    "n": 6
  },
  "audience_policies": [
    {
      "audience": "Adult",
      "age_range": null,
      "count": null,
      "form": "per-person-price",
      "value": 9
    },
    {
      "audience": "Child",
      "age_range": null,
      "count": null,
      "form": "per-person-price",
      "value": 6
    },
    {
      "audience": "Child",
      "age_range": {
        "min": null,
        "max": 1
      },
      "count": null,
      "form": "free",
      "value": null
    }
  ],
  "restrictions": {
    "blackout_dates": [],
    "weekdays_only": false,
    "seasonal": null,
    "reservation_required": false
  },
  "source_phrases": {
    "capacity.n": "maximum of 6 people",
    "audience_policies[0].form": "$9 per adult",
    "audience_policies[1].form": "$6 per child",
    "audience_policies[2].age_range": "Children under 2 are admitted free"
  }
}