{
  "library_id": "wilmington",
  "attraction_slug": "the-discovery-museums",
  "status": "ok",
  "raw": "Pass admits 3 people at half price. ($9.50 instead of $19.00) No payment will be collected online, you will pay when you arrive. Note: The museum is closed on Mondays",
  "capacity": {
    "kind": "people",
    "n": 3
  },
  "audience_policies": [
    {
      "audience": "Everyone",
      "age_range": null,
      "count": null,
      "form": "percent-off",
      "value": 50
    }
  ],
  "restrictions": {
    "blackout_dates": [],
    "weekdays_only": false,
    "seasonal": null,
    "reservation_required": false
  },
  "source_phrases": {
    "capacity.n": "admits 3 people",
    "audience_policies[0].form": "half price"
  }
}