{
  "library_id": "woburn",
  "extracted_at": "2026-05-29T00:00:00Z",
  "sources_inspected": ["_pages/woburn.html"],
  "card_eligibility": {
    "source_phrase": "To get a free Library Card, you must be a Massachusetts resident.",
    "source_block": "To get a free Library Card, you must\n\nbe a Massachusetts resident.\n\nbring a picture I.D. with current address or a picture I.D. and a bill/mail received at your current address.*\n\nbe at least 4 years old OR be able to write your own full name (whichever comes first).\n\nhave a parent or guardian sign your application if you are under 12 years old.",
    "source_url": "https://woburnpubliclibrary.org/services/how-to-get-a-library-card/",
    "source_path": "_pages/woburn.html",
    "source_confidence": "high"
  }
}
