{
  "slug": "christian-science-plaza",
  "status": "ok",
  "regular_hours": {
    "mon": "10:00 AM – 5:00 PM",
    "tue": "10:00 AM – 5:00 PM",
    "wed": "10:00 AM – 5:00 PM",
    "thu": "10:00 AM – 5:00 PM",
    "fri": "10:00 AM – 5:00 PM",
    "sat": "10:00 AM – 5:00 PM",
    "sun": "11:00 AM – 5:00 PM"
  },
  "notes": "Hours apply to the 'How Do You See the World?' interactive experience. Mary Baker Eddy Library is open Mon–Thu 11:00 AM – 3:00 PM.",
  "source": "admission_html",
  "source_url": "https://www.christianscience.com/visit"
}
